paddleocr_convert/__init__.py
paddleocr_convert/main.py
paddleocr_convert/utils.py
paddleocr_convert-0.1.0.dist-info/LICENSE
paddleocr_convert-0.1.0.dist-info/METADATA
paddleocr_convert-0.1.0.dist-info/WHEEL
paddleocr_convert-0.1.0.dist-info/entry_points.txt
paddleocr_convert-0.1.0.dist-info/top_level.txt
paddleocr_convert-0.1.0.dist-info/RECORD
