Metadata-Version: 2.1
Name: paddleocr-convert
Version: 0.1.0
Summary: Tool for converting the PaddleOCR model to onnx format.
Home-page: https://github.com/RapidAI/PaddleOCRModelConvert
Download-URL: https://github.com/RapidAI/PaddleOCRModelConvert.git
Author: SWHL
Author-email: liekkaskono@163.com
License: Apache-2.0
Keywords: ocr,text_detection,text_recognition,db,onnxruntime,paddleocr,openvino,rapidocr
Platform: Any
Classifier: Programming Language :: Python :: 3.6
Classifier: Programming Language :: Python :: 3.7
Classifier: Programming Language :: Python :: 3.8
Classifier: Programming Language :: Python :: 3.9
Classifier: Programming Language :: Python :: 3.10
Classifier: Programming Language :: Python :: 3.11
Classifier: Programming Language :: Python :: 3.12
Classifier: Programming Language :: Python :: 3.13
Requires-Python: >=3.6
License-File: LICENSE
Requires-Dist: onnx>=1.12.0
Requires-Dist: requests>=2.27.1
Requires-Dist: tqdm>=4.64.1
Requires-Dist: paddle2onnx>=1.0.0
Requires-Dist: colorlog
Requires-Dist: paddlepaddle==3.1.0
